xls2txt/__init__.py
xls2txt/main.py
xls2txt-1.1.1.dist-info/entry_points.txt
xls2txt-1.1.1.dist-info/LICENSE
xls2txt-1.1.1.dist-info/WHEEL
xls2txt-1.1.1.dist-info/METADATA
xls2txt-1.1.1.dist-info/RECORD
